rrg/__init__.py
rrg/app.py
rrg/archive.py
rrg/billing.py
rrg/commissions.py
rrg/employees.py
rrg/helpers.py
rrg/invoices.py
rrg/jos_models.py
rrg/maintenance.py
rrg/models.py
rrg/payroll.py
rrg/queries.py
rrg/reminders.py
rrg/reminders_generation.py
rrg/renderers.py
rrg/sales.py
rrg/sherees_commissions.py
rrg/timecards.py
rrg/utils.py
rrg/workers_comp.py
rrg/reports/__init__.py
rrg/reports/invoices.py
rrg/scripts/__init__.py
rrg/scripts/ar_report.py
rrg/scripts/assemble_clients_cache.py
rrg/scripts/assemble_contracts_cache.py
rrg/scripts/assemble_employees_cache.py
rrg/scripts/backup_data_to_s3.py
rrg/scripts/backup_db.py
rrg/scripts/cache_client_memos.py
rrg/scripts/cache_clients.py
rrg/scripts/cache_clients_ar.py
rrg/scripts/cache_clients_checks.py
rrg/scripts/cache_clients_managers.py
rrg/scripts/cache_comm_items.py
rrg/scripts/cache_comm_payments.py
rrg/scripts/cache_contract_items.py
rrg/scripts/cache_contracts.py
rrg/scripts/cache_employee_memos.py
rrg/scripts/cache_employees.py
rrg/scripts/cache_employees_payments.py
rrg/scripts/cache_expenses.py
rrg/scripts/cache_invoices.py
rrg/scripts/cache_invoices_items.py
rrg/scripts/cache_invoices_payments.py
rrg/scripts/cache_payrolls.py
rrg/scripts/cache_sherees_invoices.py
rrg/scripts/cache_sherees_invoices_items.py
rrg/scripts/cache_states.py
rrg/scripts/cache_vendors.py
rrg/scripts/cached_contract.py
rrg/scripts/cached_contracts.py
rrg/scripts/cached_employee.py
rrg/scripts/cached_employee_contracts.py
rrg/scripts/cached_employees.py
rrg/scripts/commissions.py
rrg/scripts/commissions_monthly_summaries.py
rrg/scripts/commissions_monthly_summary.py
rrg/scripts/delete_old_voided_inv.py
rrg/scripts/delete_old_zero_iitems.py
rrg/scripts/download_last_db_backup.py
rrg/scripts/edit_employee.py
rrg/scripts/edit_open_invoice.py
rrg/scripts/edit_timecard.py
rrg/scripts/employees.py
rrg/scripts/forget_reminder.py
rrg/scripts/get_last_backup.py
rrg-0.0.175.dist-info/DESCRIPTION.rst
rrg-0.0.175.dist-info/METADATA
rrg-0.0.175.dist-info/RECORD
rrg-0.0.175.dist-info/WHEEL
rrg-0.0.175.dist-info/entry_points.txt
rrg-0.0.175.dist-info/metadata.json
rrg-0.0.175.dist-info/top_level.txt
