Metadata-Version: 2.0
Name: rrg
Version: 0.0.175
Summary: Utility Library for Taking AR report generating out of CakePHP DB
Home-page: https://github.com/fogcitymarathoner/rrg
Author: Marc Condon
Author-email: marc@sfgeek.net
License: MIT
Keywords: CakePHP MySQL XML
Platform: UNKNOWN
Classifier: Development Status :: 1 - Planning
Classifier: Intended Audience :: Developers
Classifier: Topic :: Utilities
Classifier: License :: OSI Approved :: MIT License
Classifier: Programming Language :: Python :: 2.7
Requires-Dist: Flask
Requires-Dist: Flask-Script
Requires-Dist: gunicorn
Requires-Dist: mysql-python
Requires-Dist: python-keyczar
Requires-Dist: s3-mysql-backup
Requires-Dist: sqlalchemy
Requires-Dist: tabulate
Provides-Extra: dev
Requires-Dist: check-manifest; extra == 'dev'
Provides-Extra: test
Requires-Dist: coverage; extra == 'test'
